{
 "Data":[
  {
    "id":"1",
    "name":"Sweta Manna"
  },
  {
    "id":"2",
    "name":"Bonya Roy"
  },
  {
    "id":"3",
    "name":"Abhirup Roy"
  },
  {
    "id":"4",
    "name":"Prerona Bandopadhay"
  },
  {
    "id":"5",
    "name":"Izaz Ahmed"
  },
  {
    "id":"6",
    "name":"ImanKalyan Nag"
  },
  {
    "id":"7",
    "name":"Aishik Dutta"
  },
  {
    "id":"8",
    "name":"Aniruddha Patra"
  },
  {
    "id":"9",
    "name":"Disha Banerjee"
  },
  {
    "id":"10",
    "name":"Asmita Roy"
  },
  {
    "id":"11",
    "name":"Subhodip Chakraborty"
  },
  {
    "id":"12",
    "name":"Ankita Roy"
  },
  {
    "id":"13",
    "name":"Sujit Dhor"
  },
  {
    "id":"14",
    "name":"Smiti Chakraborty"
  },
  {
    "id":"15",
    "name":"Akash Chakraborty"
  },
  {
    "id":"16",
    "name":"Santi Priya Sarkar"
  },
  {
    "id":"17",
    "name":"Avijit Mitra"
  },
  {
    "id":"18",
    "name":"Sangita Shaw"
  },
  {
    "id":"19",
    "name":"Suvendu Patra"
  },
  {
    "id":"20",
    "name":"Manish Banerjee"
  },
  {
    "id":"21",
    "name":"Surjyatapa Sarkar"
  },
  {
    "id":"22",
    "name":"Riya Ghosh"
  },
  {
    "id":"23",
    "name":"Debolina Saha"
  },
  {
    "id":"24",
    "name":"Soumyajit Chakraborty"
  },
  {
    "id":"25",
    "name":"Suranjan Naiya"
  },
  {
    "id":"26",
    "name":"Debosmita Chakraborty"
  },
  {
    "id":"27",
    "name":"Rupam Biswas"
  },
  {
    "id":"28",
    "name":"Aniket Ghosh"
  },
  {
    "id":"29",
    "name":"Poonam Kumari Prasad"
  }
 ]
}
